README.rst
setup.py
pynvrtc/__init__.py
pynvrtc/compiler.py
pynvrtc/interface.py
pynvrtc.egg-info/PKG-INFO
pynvrtc.egg-info/SOURCES.txt
pynvrtc.egg-info/dependency_links.txt
pynvrtc.egg-info/top_level.txt